Metadata-Version: 2.1
Name: django-postgres-extensions-up
Version: 0.9.4
Summary: Extra features for django.contrib.postgres
Home-page: https://github.com/vasanski/django_postgres_extensions
Author: Eduard Vasanski
Author-email: eduard.vasanski@gmail.com
License: UNKNOWN
Platform: UNKNOWN
Classifier: Development Status :: 4 - Beta
Classifier: Environment :: Web Environment
Classifier: Framework :: Django
Classifier: Intended Audience :: Developers
Classifier: License :: OSI Approved :: BSD License
Classifier: Operating System :: OS Independent
Classifier: Programming Language :: Python
Classifier: Programming Language :: Python :: 2
Classifier: Programming Language :: Python :: 3
Classifier: Topic :: Database
Classifier: Topic :: Software Development :: Libraries :: Python Modules
License-File: LICENSE
